eater/__init__.py
eater/errors.py
eater/api/__init__.py
eater/api/base.py
eater/api/http.py
eater/tests/__init__.py
eater/tests/api/__init__.py
eater/tests/api/test_base.py
eater/tests/api/test_http.py
eater-0.4.0.dist-info/DESCRIPTION.rst
eater-0.4.0.dist-info/METADATA
eater-0.4.0.dist-info/RECORD
eater-0.4.0.dist-info/WHEEL
eater-0.4.0.dist-info/metadata.json
eater-0.4.0.dist-info/top_level.txt
