Metadata-Version: 2.0
Name: eater
Version: 0.4.0
Summary: Consume APIs and hold them to account.
Home-page: http://github.com/alexhayes/eater
Author: Alex Hayes
Author-email: alex@alution.com
License: MIT
Keywords: schematics,xml,model,modelling,dicttoxml,xmltodict
Platform: any
Classifier: Development Status :: 4 - Beta
Classifier: License :: OSI Approved :: MIT License
Classifier: Topic :: Other/Nonlisted Topic
Classifier: Topic :: Software Development :: Libraries :: Python Modules
Classifier: Intended Audience :: Developers
Classifier: Programming Language :: Python
Classifier: Programming Language :: Python :: 3
Classifier: Programming Language :: Python :: 3.5
Classifier: Programming Language :: Python :: Implementation :: CPython
Classifier: Programming Language :: Python :: Implementation :: PyPy
Classifier: Operating System :: OS Independent
Classifier: Operating System :: POSIX
Classifier: Operating System :: Microsoft :: Windows
Classifier: Operating System :: MacOS :: MacOS X
Requires-Dist: schematics (==2.0.0a1)
Requires-Dist: requests (==2.12.1)
